{
    "AAPL": {
        "Open": 0.3723210096359253,
        "High": 0.3787499964237213,
        "Low": 0.36446401476860046,
        "Close": 0.36660701036453247,
        "Adj Close": 0.30757012963294983,
        "Volume": 250611200.0
    },
    "ABBV": {
        "Open": null,
        "High": null,
        "Low": null,
        "Close": null,
        "Adj Close": null,
        "Volume": null
    },
    "ABT": {
        "Open": 24.141889572143555,
        "High": 24.465097427368164,
        "Low": 24.128421783447266,
        "Close": 24.281049728393555,
        "Adj Close": 12.956451416015625,
        "Volume": 5369782.0
    },
    "ACN": {
        "Open": 22.0,
        "High": 22.100000381469727,
        "Low": 20.860000610351562,
        "Close": 21.850000381469727,
        "Adj Close": 15.272486686706543,
        "Volume": 1415900.0
    },
    "ADBE": {
        "Open": 16.905000686645508,
        "High": 16.90999984741211,
        "Low": 16.010000228881836,
        "Close": 16.030000686645508,
        "Adj Close": 15.948873519897461,
        "Volume": 6677800.0
    },
    "AIG": {
        "Open": 1654.0,
        "High": 1670.0,
        "Low": 1646.4000244140625,
        "Close": 1656.0,
        "Adj Close": 978.836181640625,
        "Volume": 246970.0
    },
    "AMD": {
        "Open": 13.800000190734863,
        "High": 13.800000190734863,
        "Low": 13.130000114440918,
        "Close": 13.210000038146973,
        "Adj Close": 13.210000038146973,
        "Volume": 4157200.0
    },
    "AMGN": {
        "Open": 65.19999694824219,
        "High": 65.87000274658203,
        "Low": 64.12000274658203,
        "Close": 64.5199966430664,
        "Adj Close": 43.64060592651367,
        "Volume": 7623600.0
    },
    "AMT": {
        "Open": 9.25,
        "High": 9.699999809265137,
        "Low": 8.8100004196167,
        "Close": 9.199999809265137,
        "Adj Close": 6.726839065551758,
        "Volume": 3067000.0
    },
    "AMZN": {
        "Open": 0.5619999766349792,
        "High": 0.6200000047683716,
        "Low": 0.5590000152587891,
        "Close": 0.5795000195503235,
        "Adj Close": 0.5795000195503235,
        "Volume": 970324000.0
    },
    "AVGO": {
        "Open": null,
        "High": null,
        "Low": null,
        "Close": null,
        "Adj Close": null,
        "Volume": null
    },
    "AXP": {
        "Open": 29.795211791992188,
        "High": 30.329145431518555,
        "Low": 29.37506866455078,
        "Close": 29.45384407043457,
        "Adj Close": 21.006755828857422,
        "Volume": 4142694.0
    },
    "BA": {
        "Open": 35.13999938964844,
        "High": 35.13999938964844,
        "Low": 33.95000076293945,
        "Close": 34.16999816894531,
        "Adj Close": 22.634145736694336,
        "Volume": 3843000.0
    },
    "BAC": {
        "Open": 31.649999618530273,
        "High": 31.950000762939453,
        "Low": 30.854999542236328,
        "Close": 30.854999542236328,
        "Adj Close": 17.035991668701172,
        "Volume": 15635600.0
    },
    "BK": {
        "Open": 42.39982986450195,
        "High": 42.781429290771484,
        "Low": 41.06423568725586,
        "Close": 41.06423568725586,
        "Adj Close": 23.173128128051758,
        "Volume": 2598595.0
    },
    "BKNG": {
        "Open": 24.420000076293945,
        "High": 24.899999618530273,
        "Low": 24.0,
        "Close": 24.059999465942383,
        "Adj Close": 23.67265510559082,
        "Volume": 259700.0
    },
    "BLK": {
        "Open": 40.849998474121094,
        "High": 40.849998474121094,
        "Low": 40.29999923706055,
        "Close": 40.380001068115234,
        "Adj Close": 24.165218353271484,
        "Volume": 48100.0
    },
    "BMY": {
        "Open": 53.599998474121094,
        "High": 54.150001525878906,
        "Low": 53.599998474121094,
        "Close": 54.0,
        "Adj Close": 21.127107620239258,
        "Volume": 5416700.0
    },
    "BRK-B": {
        "Open": 45.0,
        "High": 45.599998474121094,
        "Low": 44.84000015258789,
        "Close": 45.459999084472656,
        "Adj Close": 45.459999084472656,
        "Volume": 310000.0
    },
    "C": {
        "Open": 500.0,
        "High": 502.20001220703125,
        "Low": 477.5,
        "Close": 478.0,
        "Adj Close": 254.2388153076172,
        "Volume": 2365120.0
    },
    "CAT": {
        "Open": 24.350000381469727,
        "High": 24.350000381469727,
        "Low": 24.0,
        "Close": 24.094999313354492,
        "Adj Close": 13.251913070678711,
        "Volume": 2016200.0
    },
    "CL": {
        "Open": 28.895000457763672,
        "High": 29.235000610351562,
        "Low": 28.725000381469727,
        "Close": 28.975000381469727,
        "Adj Close": 16.840906143188477,
        "Volume": 2011600.0
    },
    "CMCSA": {
        "Open": 12.146203994750977,
        "High": 12.183692932128906,
        "Low": 11.980630874633789,
        "Close": 12.018118858337402,
        "Adj Close": 8.155081748962402,
        "Volume": 325542.0
    },
    "COF": {
        "Open": 54.20000076293945,
        "High": 54.209999084472656,
        "Low": 52.0,
        "Close": 52.040000915527344,
        "Adj Close": 37.829795837402344,
        "Volume": 1778000.0
    },
    "COP": {
        "Open": 20.811241149902344,
        "High": 21.188589096069336,
        "Low": 20.601604461669922,
        "Close": 20.826488494873047,
        "Adj Close": 9.61772346496582,
        "Volume": 5616564.0
    },
    "COST": {
        "Open": 42.4900016784668,
        "High": 42.4900016784668,
        "Low": 40.84000015258789,
        "Close": 40.86000061035156,
        "Adj Close": 27.260448455810547,
        "Volume": 4011700.0
    },
    "CRM": {
        "Open": null,
        "High": null,
        "Low": null,
        "Close": null,
        "Adj Close": null,
        "Volume": null
    },
    "CSCO": {
        "Open": 19.5,
        "High": 19.959999084472656,
        "Low": 18.84000015258789,
        "Close": 18.8799991607666,
        "Adj Close": 12.216330528259277,
        "Volume": 59998800.0
    },
    "CVS": {
        "Open": 13.75,
        "High": 13.975000381469727,
        "Low": 13.5,
        "Close": 13.75,
        "Adj Close": 8.789556503295898,
        "Volume": 11062600.0
    },
    "CVX": {
        "Open": 42.525001525878906,
        "High": 42.95000076293945,
        "Low": 42.275001525878906,
        "Close": 42.275001525878906,
        "Adj Close": 17.048351287841797,
        "Volume": 5035000.0
    },
    "DE": {
        "Open": 19.950000762939453,
        "High": 20.125,
        "Low": 19.75,
        "Close": 20.0049991607666,
        "Adj Close": 12.591941833496094,
        "Volume": 1432800.0
    },
    "DHR": {
        "Open": 10.148995399475098,
        "High": 10.384237289428711,
        "Low": 10.123790740966797,
        "Close": 10.281739234924316,
        "Adj Close": 6.100103855133057,
        "Volume": 5547233.0
    },
    "DIS": {
        "Open": 20.71649932861328,
        "High": 20.71649932861328,
        "Low": 19.887840270996094,
        "Close": 19.937164306640625,
        "Adj Close": 15.382619857788086,
        "Volume": 6045819.0
    },
    "DUK": {
        "Open": 64.5020980834961,
        "High": 64.74616241455078,
        "Low": 62.54960250854492,
        "Close": 63.14232635498047,
        "Adj Close": 20.478870391845703,
        "Volume": 3655137.0
    },
    "EMR": {
        "Open": 26.5049991607666,
        "High": 26.75,
        "Low": 26.0,
        "Close": 26.09000015258789,
        "Adj Close": 13.475095748901367,
        "Volume": 2273400.0
    },
    "FDX": {
        "Open": 45.2599983215332,
        "High": 45.27000045776367,
        "Low": 44.349998474121094,
        "Close": 44.61000061035156,
        "Adj Close": 35.71888732910156,
        "Volume": 1064200.0
    },
    "GD": {
        "Open": 41.54999923706055,
        "High": 41.54999923706055,
        "Low": 41.064998626708984,
        "Close": 41.06999969482422,
        "Adj Close": 24.70620346069336,
        "Volume": 1251200.0
    },
    "GE": {
        "Open": 192.89559936523438,
        "High": 196.48992919921875,
        "Low": 187.5760040283203,
        "Close": 188.58241271972656,
        "Adj Close": 104.33838653564453,
        "Volume": 4960858.0
    },
    "GILD": {
        "Open": 4.481249809265137,
        "High": 4.502500057220459,
        "Low": 4.309374809265137,
        "Close": 4.328125,
        "Adj Close": 3.0069711208343506,
        "Volume": 27323200.0
    },
    "GM": {
        "Open": null,
        "High": null,
        "Low": null,
        "Close": null,
        "Adj Close": null,
        "Volume": null
    },
    "GOOG": {
        "Open": null,
        "High": null,
        "Low": null,
        "Close": null,
        "Adj Close": null,
        "Volume": null
    },
    "GOOGL": {
        "Open": null,
        "High": null,
        "Low": null,
        "Close": null,
        "Adj Close": null,
        "Volume": null
    },
    "GS": {
        "Open": 89.5999984741211,
        "High": 89.79000091552734,
        "Low": 86.5,
        "Close": 86.80999755859375,
        "Adj Close": 60.940032958984375,
        "Volume": 3780000.0
    },
    "HD": {
        "Open": 42.75,
        "High": 44.27000045776367,
        "Low": 42.650001525878906,
        "Close": 43.79999923706055,
        "Adj Close": 25.689416885375977,
        "Volume": 10684400.0
    },
    "HON": {
        "Open": 29.517614364624023,
        "High": 29.778196334838867,
        "Low": 29.032392501831055,
        "Close": 29.562541961669922,
        "Adj Close": 17.112394332885742,
        "Volume": 6161542.0
    },
    "IBM": {
        "Open": 109.08221435546875,
        "High": 109.34990692138672,
        "Low": 107.17017364501953,
        "Close": 107.21797180175781,
        "Adj Close": 55.72282409667969,
        "Volume": 6444615.0
    },
    "INTC": {
        "Open": 31.920000076293945,
        "High": 32.54999923706055,
        "Low": 31.610000610351562,
        "Close": 31.760000228881836,
        "Adj Close": 18.111440658569336,
        "Volume": 61282400.0
    },
    "INTU": {
        "Open": 19.825000762939453,
        "High": 20.989999771118164,
        "Low": 19.670000076293945,
        "Close": 20.084999084472656,
        "Adj Close": 17.6949520111084,
        "Volume": 6936000.0
    },
    "ISRG": {
        "Open": 2.042222023010254,
        "High": 2.042222023010254,
        "Low": 2.0088889598846436,
        "Close": 2.0088889598846436,
        "Adj Close": 2.0088889598846436,
        "Volume": 464400.0
    },
    "JNJ": {
        "Open": 60.0,
        "High": 60.22999954223633,
        "Low": 59.900001525878906,
        "Close": 59.9900016784668,
        "Adj Close": 31.300703048706055,
        "Volume": 7277100.0
    },
    "JPM": {
        "Open": 39.4900016784668,
        "High": 39.63999938964844,
        "Low": 37.20000076293945,
        "Close": 37.5,
        "Adj Close": 18.728788375854492,
        "Volume": 18051800.0
    },
    "KO": {
        "Open": 23.604999542236328,
        "High": 23.690000534057617,
        "Low": 23.28499984741211,
        "Close": 23.375,
        "Adj Close": 11.693863868713379,
        "Volume": 9075800.0
    },
    "LIN": {
        "Open": 26.170000076293945,
        "High": 26.44499969482422,
        "Low": 26.049999237060547,
        "Close": 26.174999237060547,
        "Adj Close": 16.83283042907715,
        "Volume": 1410200.0
    },
    "LLY": {
        "Open": 82.44999694824219,
        "High": 82.63999938964844,
        "Low": 81.16000366210938,
        "Close": 81.44999694824219,
        "Adj Close": 41.583621978759766,
        "Volume": 1888900.0
    },
    "LMT": {
        "Open": 46.099998474121094,
        "High": 46.5,
        "Low": 45.349998474121094,
        "Close": 45.61000061035156,
        "Adj Close": 24.21297264099121,
        "Volume": 1285100.0
    },
    "LOW": {
        "Open": 21.56999969482422,
        "High": 21.899999618530273,
        "Low": 21.375,
        "Close": 21.844999313354492,
        "Adj Close": 15.32579517364502,
        "Volume": 11790000.0
    },
    "MA": {
        "Open": null,
        "High": null,
        "Low": null,
        "Close": null,
        "Adj Close": null,
        "Volume": null
    },
    "MCD": {
        "Open": 27.010000228881836,
        "High": 27.100000381469727,
        "Low": 26.5,
        "Close": 26.760000228881836,
        "Adj Close": 14.424189567565918,
        "Volume": 7836600.0
    },
    "MDLZ": {
        "Open": 33.0,
        "High": 33.279998779296875,
        "Low": 32.84000015258789,
        "Close": 32.95000076293945,
        "Adj Close": 11.857430458068848,
        "Volume": 1108400.0
    },
    "MDT": {
        "Open": 44.900001525878906,
        "High": 46.13999938964844,
        "Low": 44.68000030517578,
        "Close": 45.779998779296875,
        "Adj Close": 28.80826759338379,
        "Volume": 8984100.0
    },
    "MET": {
        "Open": 24.24242401123047,
        "High": 24.349376678466797,
        "Low": 24.108734130859375,
        "Close": 24.2869873046875,
        "Adj Close": 13.48069953918457,
        "Volume": 1582693.0
    },
    "META": {
        "Open": null,
        "High": null,
        "Low": null,
        "Close": null,
        "Adj Close": null,
        "Volume": null
    },
    "MMM": {
        "Open": 48.18143844604492,
        "High": 48.42809295654297,
        "Low": 47.7717399597168,
        "Close": 47.905517578125,
        "Adj Close": 24.48838996887207,
        "Volume": 3463377.0
    },
    "MO": {
        "Open": 45.06999969482422,
        "High": 45.439998626708984,
        "Low": 44.70000076293945,
        "Close": 44.93000030517578,
        "Adj Close": 2.502643585205078,
        "Volume": 8815800.0
    },
    "MRK": {
        "Open": 63.654579162597656,
        "High": 63.902671813964844,
        "Low": 62.261451721191406,
        "Close": 62.356868743896484,
        "Adj Close": 25.14217185974121,
        "Volume": 4634990.0
    },
    "MS": {
        "Open": 57.2599983215332,
        "High": 57.47999954223633,
        "Low": 54.04999923706055,
        "Close": 54.20000076293945,
        "Adj Close": 26.93505859375,
        "Volume": 6064900.0
    },
    "MSFT": {
        "Open": 31.584999084472656,
        "High": 32.060001373291016,
        "Low": 31.364999771118164,
        "Close": 31.399999618530273,
        "Adj Close": 19.18088150024414,
        "Volume": 54536600.0
    },
    "NEE": {
        "Open": 6.875,
        "High": 6.900000095367432,
        "Low": 6.775000095367432,
        "Close": 6.824999809265137,
        "Adj Close": 3.2419114112854004,
        "Volume": 6945600.0
    },
    "NFLX": {
        "Open": null,
        "High": null,
        "Low": null,
        "Close": null,
        "Adj Close": null,
        "Volume": null
    },
    "NKE": {
        "Open": 6.502500057220459,
        "High": 6.512499809265137,
        "Low": 6.40625,
        "Close": 6.46999979019165,
        "Adj Close": 4.860157489776611,
        "Volume": 6448800.0
    },
    "NOW": {
        "Open": null,
        "High": null,
        "Low": null,
        "Close": null,
        "Adj Close": null,
        "Volume": null
    },
    "NVDA": {
        "Open": 0.4449999928474426,
        "High": 0.4524169862270355,
        "Low": 0.4269999861717224,
        "Close": 0.42800000309944153,
        "Adj Close": 0.39240527153015137,
        "Volume": 740844000.0
    },
    "ORCL": {
        "Open": 14.319999694824219,
        "High": 14.880000114440918,
        "Low": 14.069999694824219,
        "Close": 14.119999885559082,
        "Adj Close": 11.289495468139648,
        "Volume": 30083900.0
    },
    "PEP": {
        "Open": 48.68000030517578,
        "High": 48.70000076293945,
        "Low": 48.02000045776367,
        "Close": 48.45000076293945,
        "Adj Close": 25.536863327026367,
        "Volume": 3318900.0
    },
    "PFE": {
        "Open": 41.28083419799805,
        "High": 41.49905014038086,
        "Low": 40.958255767822266,
        "Close": 40.958255767822266,
        "Adj Close": 15.817363739013672,
        "Volume": 8452869.0
    },
    "PG": {
        "Open": 38.42499923706055,
        "High": 38.625,
        "Low": 37.974998474121094,
        "Close": 38.0,
        "Adj Close": 19.80287742614746,
        "Volume": 5393400.0
    },
    "PLTR": {
        "Open": null,
        "High": null,
        "Low": null,
        "Close": null,
        "Adj Close": null,
        "Volume": null
    },
    "PM": {
        "Open": null,
        "High": null,
        "Low": null,
        "Close": null,
        "Adj Close": null,
        "Volume": null
    },
    "PYPL": {
        "Open": null,
        "High": null,
        "Low": null,
        "Close": null,
        "Adj Close": null,
        "Volume": null
    },
    "QCOM": {
        "Open": 29.809999465942383,
        "High": 30.299999237060547,
        "Low": 28.614999771118164,
        "Close": 28.645000457763672,
        "Adj Close": 17.74423599243164,
        "Volume": 27288400.0
    },
    "RTX": {
        "Open": 18.596601486206055,
        "High": 18.974197387695312,
        "Low": 18.533668518066406,
        "Close": 18.609188079833984,
        "Adj Close": 11.041722297668457,
        "Volume": 5922203.0
    },
    "SBUX": {
        "Open": 4.267499923706055,
        "High": 4.335000038146973,
        "Low": 4.1875,
        "Close": 4.227499961853027,
        "Adj Close": 3.136927843093872,
        "Volume": 15805200.0
    },
    "SCHW": {
        "Open": 15.199999809265137,
        "High": 15.199999809265137,
        "Low": 14.329999923706055,
        "Close": 14.399999618530273,
        "Adj Close": 10.440411567687988,
        "Volume": 3552400.0
    },
    "SO": {
        "Open": 23.450000762939453,
        "High": 23.489999771118164,
        "Low": 22.799999237060547,
        "Close": 23.0,
        "Adj Close": 7.8340349197387695,
        "Volume": 2225000.0
    },
    "SPG": {
        "Open": 26.591299057006836,
        "High": 27.008962631225586,
        "Low": 26.591299057006836,
        "Close": 26.804771423339844,
        "Adj Close": 9.366436958312988,
        "Volume": 527397.0
    },
    "T": {
        "Open": 28.549848556518555,
        "High": 28.8066463470459,
        "Low": 28.3308162689209,
        "Close": 28.406343460083008,
        "Adj Close": 5.303182125091553,
        "Volume": 8757068.0
    },
    "TGT": {
        "Open": 37.97999954223633,
        "High": 38.689998626708984,
        "Low": 37.29999923706055,
        "Close": 38.150001525878906,
        "Adj Close": 22.55263900756836,
        "Volume": 3562300.0
    },
    "TMO": {
        "Open": 22.299999237060547,
        "High": 22.34000015258789,
        "Low": 22.0,
        "Close": 22.149999618530273,
        "Adj Close": 20.976472854614258,
        "Volume": 1008700.0
    },
    "TMUS": {
        "Open": null,
        "High": null,
        "Low": null,
        "Close": null,
        "Adj Close": null,
        "Volume": null
    },
    "TSLA": {
        "Open": null,
        "High": null,
        "Low": null,
        "Close": null,
        "Adj Close": null,
        "Volume": null
    },
    "TXN": {
        "Open": 32.0,
        "High": 32.4900016784668,
        "Low": 30.75,
        "Close": 31.030000686645508,
        "Adj Close": 18.96486473083496,
        "Volume": 7794900.0
    },
    "UBER": {
        "Open": null,
        "High": null,
        "Low": null,
        "Close": null,
        "Adj Close": null,
        "Volume": null
    },
    "UNH": {
        "Open": 17.78499984741211,
        "High": 18.049999237060547,
        "Low": 17.697500228881836,
        "Close": 17.924999237060547,
        "Adj Close": 13.914721488952637,
        "Volume": 6678000.0
    },
    "UNP": {
        "Open": 13.762499809265137,
        "High": 13.887499809265137,
        "Low": 13.637499809265137,
        "Close": 13.637499809265137,
        "Adj Close": 8.45244312286377,
        "Volume": 2019200.0
    },
    "UPS": {
        "Open": 55.22999954223633,
        "High": 55.380001068115234,
        "Low": 55.0,
        "Close": 55.18000030517578,
        "Adj Close": 27.291461944580078,
        "Volume": 1591900.0
    },
    "USB": {
        "Open": 18.420000076293945,
        "High": 18.6200008392334,
        "Low": 18.34000015258789,
        "Close": 18.399999618530273,
        "Adj Close": 8.147499084472656,
        "Volume": 3987600.0
    },
    "V": {
        "Open": null,
        "High": null,
        "Low": null,
        "Close": null,
        "Adj Close": null,
        "Volume": null
    },
    "VZ": {
        "Open": 43.17648696899414,
        "High": 43.841983795166016,
        "Low": 42.98762893676758,
        "Close": 43.0325927734375,
        "Adj Close": 12.952006340026855,
        "Volume": 5623899.0
    },
    "WFC": {
        "Open": 21.6299991607666,
        "High": 21.780000686645508,
        "Low": 21.329999923706055,
        "Close": 21.329999923706055,
        "Adj Close": 10.927620887756348,
        "Volume": 8893600.0
    },
    "WMT": {
        "Open": 18.299999237060547,
        "High": 18.586666107177734,
        "Low": 18.15999984741211,
        "Close": 18.333332061767578,
        "Adj Close": 11.80576229095459,
        "Volume": 22408200.0
    }
}