{
    "AAPL": {
        "Open": 0.3678570091724396,
        "High": 0.3696430027484894,
        "Low": 0.36053600907325745,
        "Close": 0.36464300751686096,
        "Adj Close": 0.30592241883277893,
        "Volume": 202764800.0
    },
    "ABBV": {
        "Open": null,
        "High": null,
        "Low": null,
        "Close": null,
        "Adj Close": null,
        "Volume": null
    },
    "ABT": {
        "Open": 24.24064826965332,
        "High": 24.57732391357422,
        "Low": 24.074554443359375,
        "Close": 24.4875431060791,
        "Adj Close": 13.066635131835938,
        "Volume": 5923802.0
    },
    "ACN": {
        "Open": 21.829999923706055,
        "High": 22.239999771118164,
        "Low": 21.010000228881836,
        "Close": 21.43000030517578,
        "Adj Close": 14.97891902923584,
        "Volume": 1326400.0
    },
    "ADBE": {
        "Open": 16.155000686645508,
        "High": 16.825000762939453,
        "Low": 16.155000686645508,
        "Close": 16.809999465942383,
        "Adj Close": 16.724925994873047,
        "Volume": 5866800.0
    },
    "AIG": {
        "Open": 1658.0,
        "High": 1676.800048828125,
        "Low": 1650.199951171875,
        "Close": 1663.0,
        "Adj Close": 982.973876953125,
        "Volume": 216530.0
    },
    "AMD": {
        "Open": 12.979999542236328,
        "High": 13.699999809265137,
        "Low": 12.5,
        "Close": 13.529999732971191,
        "Adj Close": 13.529999732971191,
        "Volume": 8632000.0
    },
    "AMGN": {
        "Open": 64.72000122070312,
        "High": 65.87999725341797,
        "Low": 63.93000030517578,
        "Close": 65.79000091552734,
        "Adj Close": 44.499610900878906,
        "Volume": 6988300.0
    },
    "AMT": {
        "Open": 9.1899995803833,
        "High": 9.489999771118164,
        "Low": 9.010000228881836,
        "Close": 9.350000381469727,
        "Adj Close": 6.836513519287109,
        "Volume": 2000200.0
    },
    "AMZN": {
        "Open": 0.5945000052452087,
        "High": 0.5950000286102295,
        "Low": 0.5394999980926514,
        "Close": 0.5575000047683716,
        "Adj Close": 0.5575000047683716,
        "Volume": 405480000.0
    },
    "AVGO": {
        "Open": null,
        "High": null,
        "Low": null,
        "Close": null,
        "Adj Close": null,
        "Volume": null
    },
    "AXP": {
        "Open": 29.45384407043457,
        "High": 29.45384407043457,
        "Low": 28.534780502319336,
        "Close": 29.164995193481445,
        "Adj Close": 20.800745010375977,
        "Volume": 5973838.0
    },
    "BA": {
        "Open": 34.70000076293945,
        "High": 35.20000076293945,
        "Low": 34.310001373291016,
        "Close": 35.150001525878906,
        "Adj Close": 23.28329849243164,
        "Volume": 3437100.0
    },
    "BAC": {
        "Open": 31.149999618530273,
        "High": 31.985000610351562,
        "Low": 31.125,
        "Close": 31.799999237060547,
        "Adj Close": 17.557758331298828,
        "Volume": 15955400.0
    },
    "BK": {
        "Open": 41.286834716796875,
        "High": 41.763832092285156,
        "Low": 40.44943618774414,
        "Close": 41.700233459472656,
        "Adj Close": 23.532047271728516,
        "Volume": 1893121.0
    },
    "BKNG": {
        "Open": 24.1200008392334,
        "High": 24.719999313354492,
        "Low": 24.059999465942383,
        "Close": 24.600000381469727,
        "Adj Close": 24.20395851135254,
        "Volume": 211533.0
    },
    "BLK": {
        "Open": 40.5,
        "High": 40.5,
        "Low": 38.650001525878906,
        "Close": 38.9900016784668,
        "Adj Close": 23.3333740234375,
        "Volume": 138800.0
    },
    "BMY": {
        "Open": 54.650001525878906,
        "High": 54.650001525878906,
        "Low": 53.5,
        "Close": 54.0,
        "Adj Close": 21.127107620239258,
        "Volume": 4664600.0
    },
    "BRK-B": {
        "Open": 45.720001220703125,
        "High": 47.400001525878906,
        "Low": 45.68000030517578,
        "Close": 46.68000030517578,
        "Adj Close": 46.68000030517578,
        "Volume": 425000.0
    },
    "C": {
        "Open": 478.0,
        "High": 484.8999938964844,
        "Low": 470.0,
        "Close": 483.6000061035156,
        "Adj Close": 257.2173767089844,
        "Volume": 1553420.0
    },
    "CAT": {
        "Open": 24.094999313354492,
        "High": 24.200000762939453,
        "Low": 23.774999618530273,
        "Close": 24.100000381469727,
        "Adj Close": 13.25466251373291,
        "Volume": 3087000.0
    },
    "CL": {
        "Open": 29.049999237060547,
        "High": 29.049999237060547,
        "Low": 28.5049991607666,
        "Close": 28.84000015258789,
        "Adj Close": 16.76244354248047,
        "Volume": 2637000.0
    },
    "CMCSA": {
        "Open": 12.014994621276855,
        "High": 12.083724021911621,
        "Low": 11.768197059631348,
        "Close": 12.074352264404297,
        "Adj Close": 8.193236351013184,
        "Volume": 1312090.0
    },
    "COF": {
        "Open": 52.040000915527344,
        "High": 52.5,
        "Low": 51.5,
        "Close": 51.5,
        "Adj Close": 37.43724822998047,
        "Volume": 2321600.0
    },
    "COP": {
        "Open": 20.830299377441406,
        "High": 21.459211349487305,
        "Low": 20.830299377441406,
        "Close": 21.386791229248047,
        "Adj Close": 9.87647819519043,
        "Volume": 5403005.0
    },
    "COST": {
        "Open": 41.029998779296875,
        "High": 41.599998474121094,
        "Low": 40.630001068115234,
        "Close": 41.2599983215332,
        "Adj Close": 27.527307510375977,
        "Volume": 2887600.0
    },
    "CRM": {
        "Open": null,
        "High": null,
        "Low": null,
        "Close": null,
        "Adj Close": null,
        "Volume": null
    },
    "CSCO": {
        "Open": 19.219999313354492,
        "High": 20.010000228881836,
        "Low": 19.1200008392334,
        "Close": 19.889999389648438,
        "Adj Close": 12.869856834411621,
        "Volume": 72872400.0
    },
    "CVS": {
        "Open": 13.755000114440918,
        "High": 13.755000114440918,
        "Low": 13.5,
        "Close": 13.640000343322754,
        "Adj Close": 8.719236373901367,
        "Volume": 6268800.0
    },
    "CVX": {
        "Open": 42.5,
        "High": 42.84000015258789,
        "Low": 42.189998626708984,
        "Close": 42.724998474121094,
        "Adj Close": 17.229822158813477,
        "Volume": 3293000.0
    },
    "DE": {
        "Open": 20.0049991607666,
        "High": 20.0049991607666,
        "Low": 19.5,
        "Close": 19.774999618530273,
        "Adj Close": 12.447165489196777,
        "Volume": 2371400.0
    },
    "DHR": {
        "Open": 10.281739234924316,
        "High": 10.328786849975586,
        "Low": 10.006170272827148,
        "Close": 10.115388870239258,
        "Adj Close": 6.001410961151123,
        "Volume": 6872594.0
    },
    "DIS": {
        "Open": 20.18379020690918,
        "High": 20.2133846282959,
        "Low": 19.483375549316406,
        "Close": 19.98649024963379,
        "Adj Close": 15.420683860778809,
        "Volume": 7255651.0
    },
    "DUK": {
        "Open": 63.19462585449219,
        "High": 63.97911071777344,
        "Low": 62.09634780883789,
        "Close": 63.7001838684082,
        "Adj Close": 20.659807205200195,
        "Volume": 2740435.0
    },
    "EMR": {
        "Open": 26.09000015258789,
        "High": 26.549999237060547,
        "Low": 25.799999237060547,
        "Close": 26.5049991607666,
        "Adj Close": 13.689434051513672,
        "Volume": 2199200.0
    },
    "FDX": {
        "Open": 45.150001525878906,
        "High": 45.470001220703125,
        "Low": 44.45000076293945,
        "Close": 45.25,
        "Adj Close": 36.231327056884766,
        "Volume": 1339500.0
    },
    "GD": {
        "Open": 41.04999923706055,
        "High": 41.4900016784668,
        "Low": 40.875,
        "Close": 41.375,
        "Adj Close": 24.88968849182129,
        "Volume": 2107800.0
    },
    "GE": {
        "Open": 188.58241271972656,
        "High": 190.6910858154297,
        "Low": 187.5760040283203,
        "Close": 190.40353393554688,
        "Adj Close": 105.34597778320312,
        "Volume": 3211435.0
    },
    "GILD": {
        "Open": 4.303124904632568,
        "High": 4.463125228881836,
        "Low": 4.254374980926514,
        "Close": 4.458749771118164,
        "Adj Close": 3.0977232456207275,
        "Volume": 34976000.0
    },
    "GM": {
        "Open": null,
        "High": null,
        "Low": null,
        "Close": null,
        "Adj Close": null,
        "Volume": null
    },
    "GOOG": {
        "Open": null,
        "High": null,
        "Low": null,
        "Close": null,
        "Adj Close": null,
        "Volume": null
    },
    "GOOGL": {
        "Open": null,
        "High": null,
        "Low": null,
        "Close": null,
        "Adj Close": null,
        "Volume": null
    },
    "GS": {
        "Open": 86.80999755859375,
        "High": 89.5999984741211,
        "Low": 85.77999877929688,
        "Close": 89.3499984741211,
        "Adj Close": 62.72309494018555,
        "Volume": 3860100.0
    },
    "HD": {
        "Open": 44.2400016784668,
        "High": 44.4900016784668,
        "Low": 43.54999923706055,
        "Close": 44.02000045776367,
        "Adj Close": 25.818449020385742,
        "Volume": 7297700.0
    },
    "HON": {
        "Open": 29.382831573486328,
        "High": 29.921964645385742,
        "Low": 29.122249603271484,
        "Close": 29.69732666015625,
        "Adj Close": 17.190414428710938,
        "Volume": 2098363.0
    },
    "IBM": {
        "Open": 107.93498992919922,
        "High": 109.5124282836914,
        "Low": 106.8929214477539,
        "Close": 109.397705078125,
        "Adj Close": 56.855674743652344,
        "Volume": 6410620.0
    },
    "INTC": {
        "Open": 31.989999771118164,
        "High": 32.41999816894531,
        "Low": 31.15999984741211,
        "Close": 32.31999969482422,
        "Adj Close": 18.430788040161133,
        "Volume": 45961000.0
    },
    "INTU": {
        "Open": 20.325000762939453,
        "High": 21.450000762939453,
        "Low": 20.325000762939453,
        "Close": 21.21500015258789,
        "Adj Close": 18.69049072265625,
        "Volume": 7974000.0
    },
    "ISRG": {
        "Open": 2.006666898727417,
        "High": 2.1222219467163086,
        "Low": 2.0,
        "Close": 2.1222219467163086,
        "Adj Close": 2.1222219467163086,
        "Volume": 200700.0
    },
    "JNJ": {
        "Open": 58.849998474121094,
        "High": 59.209999084472656,
        "Low": 58.0,
        "Close": 58.47999954223633,
        "Adj Close": 30.51285743713379,
        "Volume": 12480300.0
    },
    "JPM": {
        "Open": 37.400001525878906,
        "High": 38.09000015258789,
        "Low": 36.5,
        "Close": 38.060001373291016,
        "Adj Close": 19.008466720581055,
        "Volume": 11981900.0
    },
    "KO": {
        "Open": 23.475000381469727,
        "High": 23.639999389648438,
        "Low": 23.229999542236328,
        "Close": 23.540000915527344,
        "Adj Close": 11.776409149169922,
        "Volume": 7146400.0
    },
    "LIN": {
        "Open": 26.024999618530273,
        "High": 26.2450008392334,
        "Low": 25.78499984741211,
        "Close": 26.024999618530273,
        "Adj Close": 16.73636245727539,
        "Volume": 1330600.0
    },
    "LLY": {
        "Open": 81.36000061035156,
        "High": 82.72000122070312,
        "Low": 81.16000366210938,
        "Close": 82.55000305175781,
        "Adj Close": 42.14521026611328,
        "Volume": 2862700.0
    },
    "LMT": {
        "Open": 45.75,
        "High": 46.70000076293945,
        "Low": 45.349998474121094,
        "Close": 46.25,
        "Adj Close": 24.61208724975586,
        "Volume": 1658100.0
    },
    "LOW": {
        "Open": 21.825000762939453,
        "High": 21.950000762939453,
        "Low": 21.454999923706055,
        "Close": 21.760000228881836,
        "Adj Close": 15.266151428222656,
        "Volume": 12745200.0
    },
    "MA": {
        "Open": null,
        "High": null,
        "Low": null,
        "Close": null,
        "Adj Close": null,
        "Volume": null
    },
    "MCD": {
        "Open": 26.600000381469727,
        "High": 26.950000762939453,
        "Low": 26.559999465942383,
        "Close": 26.790000915527344,
        "Adj Close": 14.440361022949219,
        "Volume": 2903400.0
    },
    "MDLZ": {
        "Open": 33.09000015258789,
        "High": 33.970001220703125,
        "Low": 32.900001525878906,
        "Close": 33.810001373291016,
        "Adj Close": 12.166911125183105,
        "Volume": 1991600.0
    },
    "MDT": {
        "Open": 45.900001525878906,
        "High": 46.5,
        "Low": 45.56999969482422,
        "Close": 46.45000076293945,
        "Adj Close": 29.229881286621094,
        "Volume": 5282400.0
    },
    "MET": {
        "Open": 24.2869873046875,
        "High": 24.509803771972656,
        "Low": 24.180036544799805,
        "Close": 24.349376678466797,
        "Adj Close": 13.515325546264648,
        "Volume": 6930818.0
    },
    "META": {
        "Open": null,
        "High": null,
        "Low": null,
        "Close": null,
        "Adj Close": null,
        "Volume": null
    },
    "MMM": {
        "Open": 47.905517578125,
        "High": 48.39883041381836,
        "Low": 47.72157287597656,
        "Close": 48.17307662963867,
        "Adj Close": 24.625152587890625,
        "Volume": 3238290.0
    },
    "MO": {
        "Open": 45.349998474121094,
        "High": 46.97999954223633,
        "Low": 45.25,
        "Close": 46.97999954223633,
        "Adj Close": 2.6168298721313477,
        "Volume": 8433100.0
    },
    "MRK": {
        "Open": 63.07251739501953,
        "High": 63.82633590698242,
        "Low": 62.83396911621094,
        "Close": 63.788169860839844,
        "Adj Close": 25.71927261352539,
        "Volume": 5056810.0
    },
    "MS": {
        "Open": 54.209999084472656,
        "High": 56.47999954223633,
        "Low": 53.7400016784668,
        "Close": 56.25,
        "Adj Close": 27.95381736755371,
        "Volume": 5487800.0
    },
    "MSFT": {
        "Open": 31.559999465942383,
        "High": 32.45000076293945,
        "Low": 31.475000381469727,
        "Close": 32.41999816894531,
        "Adj Close": 19.803951263427734,
        "Volume": 54034400.0
    },
    "NEE": {
        "Open": 6.8125,
        "High": 6.90625,
        "Low": 6.712500095367432,
        "Close": 6.90625,
        "Adj Close": 3.2805027961730957,
        "Volume": 4234400.0
    },
    "NFLX": {
        "Open": null,
        "High": null,
        "Low": null,
        "Close": null,
        "Adj Close": null,
        "Volume": null
    },
    "NKE": {
        "Open": 6.434999942779541,
        "High": 6.456250190734863,
        "Low": 6.386250019073486,
        "Close": 6.425000190734863,
        "Adj Close": 4.826350688934326,
        "Volume": 7641600.0
    },
    "NOW": {
        "Open": null,
        "High": null,
        "Low": null,
        "Close": null,
        "Adj Close": null,
        "Volume": null
    },
    "NVDA": {
        "Open": 0.4590829908847809,
        "High": 0.46141698956489563,
        "Low": 0.4449999928474426,
        "Close": 0.4467499852180481,
        "Adj Close": 0.4095958173274994,
        "Volume": 5135472000.0
    },
    "ORCL": {
        "Open": 14.319999694824219,
        "High": 14.5,
        "Low": 14.0,
        "Close": 14.1899995803833,
        "Adj Close": 11.345462799072266,
        "Volume": 36810100.0
    },
    "PEP": {
        "Open": 48.790000915527344,
        "High": 49.349998474121094,
        "Low": 48.04999923706055,
        "Close": 48.529998779296875,
        "Adj Close": 25.57903289794922,
        "Volume": 4012400.0
    },
    "PFE": {
        "Open": 40.967742919921875,
        "High": 41.41366195678711,
        "Low": 40.891841888427734,
        "Close": 41.25237274169922,
        "Adj Close": 15.930948257446289,
        "Volume": 9410112.0
    },
    "PG": {
        "Open": 38.04999923706055,
        "High": 38.79999923706055,
        "Low": 37.619998931884766,
        "Close": 38.720001220703125,
        "Adj Close": 20.178089141845703,
        "Volume": 7276800.0
    },
    "PLTR": {
        "Open": null,
        "High": null,
        "Low": null,
        "Close": null,
        "Adj Close": null,
        "Volume": null
    },
    "PM": {
        "Open": null,
        "High": null,
        "Low": null,
        "Close": null,
        "Adj Close": null,
        "Volume": null
    },
    "PYPL": {
        "Open": null,
        "High": null,
        "Low": null,
        "Close": null,
        "Adj Close": null,
        "Volume": null
    },
    "QCOM": {
        "Open": 28.625,
        "High": 29.299999237060547,
        "Low": 28.25,
        "Close": 29.209999084472656,
        "Adj Close": 18.094228744506836,
        "Volume": 20094800.0
    },
    "RTX": {
        "Open": 18.612335205078125,
        "High": 19.38326072692871,
        "Low": 18.533668518066406,
        "Close": 19.36752700805664,
        "Adj Close": 11.491678237915039,
        "Volume": 7926568.0
    },
    "SBUX": {
        "Open": 4.25,
        "High": 4.255000114440918,
        "Low": 4.170000076293945,
        "Close": 4.224999904632568,
        "Adj Close": 3.135072946548462,
        "Volume": 14431600.0
    },
    "SCHW": {
        "Open": 14.25,
        "High": 15.510000228881836,
        "Low": 14.079999923706055,
        "Close": 14.380000114440918,
        "Adj Close": 10.425910949707031,
        "Volume": 2871900.0
    },
    "SO": {
        "Open": 22.850000381469727,
        "High": 22.940000534057617,
        "Low": 22.700000762939453,
        "Close": 22.75,
        "Adj Close": 7.7488813400268555,
        "Volume": 2917100.0
    },
    "SPG": {
        "Open": 26.730520248413086,
        "High": 27.01824378967285,
        "Low": 26.340700149536133,
        "Close": 26.869741439819336,
        "Adj Close": 9.38913345336914,
        "Volume": 335509.0
    },
    "T": {
        "Open": 28.24773406982422,
        "High": 28.58761215209961,
        "Low": 27.58308219909668,
        "Close": 28.58761215209961,
        "Adj Close": 5.3370208740234375,
        "Volume": 11088632.0
    },
    "TGT": {
        "Open": 38.25,
        "High": 38.29999923706055,
        "Low": 37.099998474121094,
        "Close": 37.40999984741211,
        "Adj Close": 22.11518096923828,
        "Volume": 2807900.0
    },
    "TMO": {
        "Open": 22.0,
        "High": 22.389999389648438,
        "Low": 21.799999237060547,
        "Close": 22.350000381469727,
        "Adj Close": 21.165870666503906,
        "Volume": 535100.0
    },
    "TMUS": {
        "Open": null,
        "High": null,
        "Low": null,
        "Close": null,
        "Adj Close": null,
        "Volume": null
    },
    "TSLA": {
        "Open": null,
        "High": null,
        "Low": null,
        "Close": null,
        "Adj Close": null,
        "Volume": null
    },
    "TXN": {
        "Open": 31.450000762939453,
        "High": 32.099998474121094,
        "Low": 30.5,
        "Close": 32.06999969482422,
        "Adj Close": 19.600481033325195,
        "Volume": 10854100.0
    },
    "UBER": {
        "Open": null,
        "High": null,
        "Low": null,
        "Close": null,
        "Adj Close": null,
        "Volume": null
    },
    "UNH": {
        "Open": 17.875,
        "High": 17.950000762939453,
        "Low": 17.65250015258789,
        "Close": 17.825000762939453,
        "Adj Close": 13.83709716796875,
        "Volume": 3621600.0
    },
    "UNP": {
        "Open": 13.649999618530273,
        "High": 13.677499771118164,
        "Low": 13.354999542236328,
        "Close": 13.524999618530273,
        "Adj Close": 8.382713317871094,
        "Volume": 3337200.0
    },
    "UPS": {
        "Open": 55.18000030517578,
        "High": 55.29999923706055,
        "Low": 54.95000076293945,
        "Close": 55.29999923706055,
        "Adj Close": 27.350807189941406,
        "Volume": 1268500.0
    },
    "USB": {
        "Open": 18.299999237060547,
        "High": 18.530000686645508,
        "Low": 18.200000762939453,
        "Close": 18.5,
        "Adj Close": 8.191783905029297,
        "Volume": 4205300.0
    },
    "V": {
        "Open": null,
        "High": null,
        "Low": null,
        "Close": null,
        "Adj Close": null,
        "Volume": null
    },
    "VZ": {
        "Open": 43.07756042480469,
        "High": 43.302391052246094,
        "Low": 42.304141998291016,
        "Close": 42.68185806274414,
        "Adj Close": 12.846445083618164,
        "Volume": 6181985.0
    },
    "WFC": {
        "Open": 21.325000762939453,
        "High": 21.56999969482422,
        "Low": 21.25,
        "Close": 21.545000076293945,
        "Adj Close": 11.037768363952637,
        "Volume": 7298800.0
    },
    "WMT": {
        "Open": 18.366666793823242,
        "High": 18.43000030517578,
        "Low": 18.166667938232422,
        "Close": 18.21666717529297,
        "Adj Close": 11.730635643005371,
        "Volume": 17183100.0
    }
}