{
    "AAPL": {
        "Open": 0.2858929932117462,
        "High": 0.2892859876155853,
        "Low": 0.2771430015563965,
        "Close": 0.2828570008277893,
        "Adj Close": 0.2373068779706955,
        "Volume": 190064000.0
    },
    "ABBV": {
        "Open": null,
        "High": null,
        "Low": null,
        "Close": null,
        "Adj Close": null,
        "Volume": null
    },
    "ABT": {
        "Open": 20.469879150390625,
        "High": 20.685352325439453,
        "Low": 20.362144470214844,
        "Close": 20.600061416625977,
        "Adj Close": 11.224735260009766,
        "Volume": 8802834.0
    },
    "ACN": {
        "Open": 17.399999618530273,
        "High": 17.700000762939453,
        "Low": 17.100000381469727,
        "Close": 17.510000228881836,
        "Adj Close": 12.238957405090332,
        "Volume": 1707100.0
    },
    "ADBE": {
        "Open": 12.835000038146973,
        "High": 13.100000381469727,
        "Low": 12.755000114440918,
        "Close": 12.854999542236328,
        "Adj Close": 12.81389331817627,
        "Volume": 4480200.0
    },
    "AIG": {
        "Open": 1290.0,
        "High": 1300.0,
        "Low": 1281.800048828125,
        "Close": 1289.4000244140625,
        "Adj Close": 764.0885620117188,
        "Volume": 281290.0
    },
    "AMD": {
        "Open": 6.730000019073486,
        "High": 6.789999961853027,
        "Low": 6.039999961853027,
        "Close": 6.099999904632568,
        "Adj Close": 6.099999904632568,
        "Volume": 9058100.0
    },
    "AMGN": {
        "Open": 45.619998931884766,
        "High": 45.7400016784668,
        "Low": 43.900001525878906,
        "Close": 44.13999938964844,
        "Adj Close": 29.85580062866211,
        "Volume": 14634300.0
    },
    "AMT": {
        "Open": 1.649999976158142,
        "High": 1.6799999475479126,
        "Low": 1.3200000524520874,
        "Close": 1.5099999904632568,
        "Adj Close": 1.1040788888931274,
        "Volume": 1798000.0
    },
    "AMZN": {
        "Open": 0.9520000219345093,
        "High": 0.9829999804496765,
        "Low": 0.940500020980835,
        "Close": 0.9754999876022339,
        "Adj Close": 0.9754999876022339,
        "Volume": 140642000.0
    },
    "AVGO": {
        "Open": null,
        "High": null,
        "Low": null,
        "Close": null,
        "Adj Close": null,
        "Volume": null
    },
    "AXP": {
        "Open": 30.688018798828125,
        "High": 31.77338981628418,
        "Low": 30.688018798828125,
        "Close": 31.116914749145508,
        "Adj Close": 22.39035415649414,
        "Volume": 4648578.0
    },
    "BA": {
        "Open": 32.849998474121094,
        "High": 33.599998474121094,
        "Low": 32.5,
        "Close": 33.18000030517578,
        "Adj Close": 22.254528045654297,
        "Volume": 4248000.0
    },
    "BAC": {
        "Open": 33.81999969482422,
        "High": 34.275001525878906,
        "Low": 33.224998474121094,
        "Close": 33.55500030517578,
        "Adj Close": 19.210073471069336,
        "Volume": 11900600.0
    },
    "BK": {
        "Open": 26.955692291259766,
        "High": 27.877887725830078,
        "Low": 26.28789520263672,
        "Close": 26.499893188476562,
        "Adj Close": 15.303886413574219,
        "Volume": 2950672.0
    },
    "BKNG": {
        "Open": 9.539999961853027,
        "High": 9.65999984741211,
        "Low": 8.640000343322754,
        "Close": 8.880000114440918,
        "Adj Close": 8.737039566040039,
        "Volume": 590833.0
    },
    "BLK": {
        "Open": 34.75,
        "High": 35.45000076293945,
        "Low": 34.75,
        "Close": 35.25,
        "Adj Close": 21.095191955566406,
        "Volume": 225200.0
    },
    "BMY": {
        "Open": 26.649999618530273,
        "High": 27.3700008392334,
        "Low": 26.549999237060547,
        "Close": 26.899999618530273,
        "Adj Close": 10.902456283569336,
        "Volume": 6164800.0
    },
    "BRK-B": {
        "Open": 49.0,
        "High": 50.0,
        "Low": 48.900001525878906,
        "Close": 49.79999923706055,
        "Adj Close": 49.79999923706055,
        "Volume": 1225000.0
    },
    "C": {
        "Open": 364.6000061035156,
        "High": 374.0,
        "Low": 363.6000061035156,
        "Close": 368.70001220703125,
        "Adj Close": 214.0548095703125,
        "Volume": 1696000.0
    },
    "CAT": {
        "Open": 21.325000762939453,
        "High": 21.75,
        "Low": 21.299999237060547,
        "Close": 21.579999923706055,
        "Adj Close": 12.239988327026367,
        "Volume": 3155600.0
    },
    "CL": {
        "Open": 27.0,
        "High": 27.475000381469727,
        "Low": 26.799999237060547,
        "Close": 27.014999389648438,
        "Adj Close": 15.914383888244629,
        "Volume": 2787400.0
    },
    "CMCSA": {
        "Open": 7.735083103179932,
        "High": 7.8819122314453125,
        "Low": 7.550765037536621,
        "Close": 7.67260217666626,
        "Adj Close": 5.206363201141357,
        "Volume": 2793513.0
    },
    "COF": {
        "Open": 31.049999237060547,
        "High": 31.56999969482422,
        "Low": 29.09000015258789,
        "Close": 29.31999969482422,
        "Adj Close": 21.37747573852539,
        "Volume": 5055800.0
    },
    "COP": {
        "Open": 18.829219818115234,
        "High": 19.012174606323242,
        "Low": 18.61958122253418,
        "Close": 18.764421463012695,
        "Adj Close": 8.909576416015625,
        "Volume": 4344914.0
    },
    "COST": {
        "Open": 32.029998779296875,
        "High": 32.61000061035156,
        "Low": 31.899999618530273,
        "Close": 32.15999984741211,
        "Adj Close": 21.45609474182129,
        "Volume": 4750300.0
    },
    "CRM": {
        "Open": null,
        "High": null,
        "Low": null,
        "Close": null,
        "Adj Close": null,
        "Volume": null
    },
    "CSCO": {
        "Open": 12.25,
        "High": 12.789999961853027,
        "Low": 12.199999809265137,
        "Close": 12.5600004196167,
        "Adj Close": 8.12696647644043,
        "Volume": 81592700.0
    },
    "CVS": {
        "Open": 13.800000190734863,
        "High": 13.8100004196167,
        "Low": 13.40999984741211,
        "Close": 13.460000038146973,
        "Adj Close": 8.673672676086426,
        "Volume": 4200200.0
    },
    "CVX": {
        "Open": 33.974998474121094,
        "High": 34.17499923706055,
        "Low": 33.54999923706055,
        "Close": 33.75,
        "Adj Close": 13.9610595703125,
        "Volume": 6481400.0
    },
    "DE": {
        "Open": 24.350000381469727,
        "High": 24.790000915527344,
        "Low": 24.014999389648438,
        "Close": 24.5,
        "Adj Close": 15.728459358215332,
        "Volume": 4850000.0
    },
    "DHR": {
        "Open": 9.66170883178711,
        "High": 9.69531536102295,
        "Low": 9.517204284667969,
        "Close": 9.544088363647461,
        "Adj Close": 5.670352458953857,
        "Volume": 6563125.0
    },
    "DIS": {
        "Open": 16.82969093322754,
        "High": 17.747135162353516,
        "Low": 16.82969093322754,
        "Close": 17.441320419311523,
        "Adj Close": 13.599740028381348,
        "Volume": 10702484.0
    },
    "DUK": {
        "Open": 35.70278549194336,
        "High": 36.365238189697266,
        "Low": 34.39530944824219,
        "Close": 34.796268463134766,
        "Adj Close": 11.58100414276123,
        "Volume": 2425630.0
    },
    "EMR": {
        "Open": 25.440000534057617,
        "High": 25.700000762939453,
        "Low": 25.0,
        "Close": 25.5,
        "Adj Close": 13.458471298217773,
        "Volume": 2391200.0
    },
    "FDX": {
        "Open": 53.970001220703125,
        "High": 54.75,
        "Low": 53.869998931884766,
        "Close": 54.599998474121094,
        "Adj Close": 43.803062438964844,
        "Volume": 1114300.0
    },
    "GD": {
        "Open": 40.65999984741211,
        "High": 41.53499984741211,
        "Low": 40.505001068115234,
        "Close": 40.79999923706055,
        "Adj Close": 24.87932014465332,
        "Volume": 2602400.0
    },
    "GE": {
        "Open": 123.88450622558594,
        "High": 124.6033706665039,
        "Low": 118.03773498535156,
        "Close": 120.29017639160156,
        "Adj Close": 68.05648040771484,
        "Volume": 6428691.0
    },
    "GILD": {
        "Open": 4.676249980926514,
        "High": 4.677499771118164,
        "Low": 4.398749828338623,
        "Close": 4.456250190734863,
        "Adj Close": 3.095986843109131,
        "Volume": 33768800.0
    },
    "GM": {
        "Open": null,
        "High": null,
        "Low": null,
        "Close": null,
        "Adj Close": null,
        "Volume": null
    },
    "GOOG": {
        "Open": null,
        "High": null,
        "Low": null,
        "Close": null,
        "Adj Close": null,
        "Volume": null
    },
    "GOOGL": {
        "Open": null,
        "High": null,
        "Low": null,
        "Close": null,
        "Adj Close": null,
        "Volume": null
    },
    "GS": {
        "Open": 74.0999984741211,
        "High": 74.94999694824219,
        "Low": 72.83000183105469,
        "Close": 73.08000183105469,
        "Adj Close": 51.62382507324219,
        "Volume": 2810500.0
    },
    "HD": {
        "Open": 27.350000381469727,
        "High": 27.56999969482422,
        "Low": 26.440000534057617,
        "Close": 26.649999618530273,
        "Adj Close": 15.690279006958008,
        "Volume": 11611300.0
    },
    "HON": {
        "Open": 23.488292694091797,
        "High": 23.7219181060791,
        "Low": 23.092927932739258,
        "Close": 23.37148094177246,
        "Adj Close": 13.749822616577148,
        "Volume": 4585794.0
    },
    "IBM": {
        "Open": 75.04779815673828,
        "High": 75.80306243896484,
        "Low": 73.80496978759766,
        "Close": 74.17781829833984,
        "Adj Close": 38.8349723815918,
        "Volume": 8493102.0
    },
    "INTC": {
        "Open": 18.3700008392334,
        "High": 18.8799991607666,
        "Low": 18.049999237060547,
        "Close": 18.149999618530273,
        "Adj Close": 10.38723087310791,
        "Volume": 49747500.0
    },
    "INTU": {
        "Open": 26.6200008392334,
        "High": 26.950000762939453,
        "Low": 26.15999984741211,
        "Close": 26.454999923706055,
        "Adj Close": 23.306949615478516,
        "Volume": 6034200.0
    },
    "ISRG": {
        "Open": 1.455556035041809,
        "High": 1.48444402217865,
        "Low": 1.342221975326538,
        "Close": 1.4488890171051025,
        "Adj Close": 1.4488890171051025,
        "Volume": 1340100.0
    },
    "JNJ": {
        "Open": 60.099998474121094,
        "High": 60.939998626708984,
        "Low": 59.95000076293945,
        "Close": 60.27000045776367,
        "Adj Close": 31.76806640625,
        "Volume": 7055300.0
    },
    "JPM": {
        "Open": 20.600000381469727,
        "High": 21.1299991607666,
        "Low": 20.0,
        "Close": 20.200000762939453,
        "Adj Close": 10.577736854553223,
        "Volume": 12928700.0
    },
    "KO": {
        "Open": 22.325000762939453,
        "High": 22.600000381469727,
        "Low": 22.239999771118164,
        "Close": 22.260000228881836,
        "Adj Close": 11.268354415893555,
        "Volume": 10365600.0
    },
    "LIN": {
        "Open": 27.18000030517578,
        "High": 27.799999237060547,
        "Low": 26.905000686645508,
        "Close": 27.149999618530273,
        "Adj Close": 17.696701049804688,
        "Volume": 2308200.0
    },
    "LLY": {
        "Open": 58.970001220703125,
        "High": 62.900001525878906,
        "Low": 58.970001220703125,
        "Close": 62.2400016784668,
        "Adj Close": 32.2325439453125,
        "Volume": 5588400.0
    },
    "LMT": {
        "Open": 55.650001525878906,
        "High": 56.79999923706055,
        "Low": 55.150001525878906,
        "Close": 56.43000030517578,
        "Adj Close": 30.194095611572266,
        "Volume": 4514000.0
    },
    "LOW": {
        "Open": 19.989999771118164,
        "High": 20.174999237060547,
        "Low": 19.5,
        "Close": 19.735000610351562,
        "Adj Close": 13.872191429138184,
        "Volume": 6418800.0
    },
    "MA": {
        "Open": null,
        "High": null,
        "Low": null,
        "Close": null,
        "Adj Close": null,
        "Volume": null
    },
    "MCD": {
        "Open": 17.5,
        "High": 17.90999984741211,
        "Low": 16.5,
        "Close": 17.790000915527344,
        "Adj Close": 9.5891752243042,
        "Volume": 19940700.0
    },
    "MDLZ": {
        "Open": 39.97999954223633,
        "High": 40.41999816894531,
        "Low": 39.54999923706055,
        "Close": 39.599998474121094,
        "Adj Close": 14.456238746643066,
        "Volume": 948100.0
    },
    "MDT": {
        "Open": 46.790000915527344,
        "High": 47.150001525878906,
        "Low": 46.4900016784668,
        "Close": 46.84000015258789,
        "Adj Close": 29.635751724243164,
        "Volume": 3834200.0
    },
    "MET": {
        "Open": 23.957218170166016,
        "High": 24.64349365234375,
        "Low": 23.903743743896484,
        "Close": 24.153297424316406,
        "Adj Close": 13.520294189453125,
        "Volume": 3363083.0
    },
    "META": {
        "Open": null,
        "High": null,
        "Low": null,
        "Close": null,
        "Adj Close": null,
        "Volume": null
    },
    "MMM": {
        "Open": 53.66638946533203,
        "High": 54.051002502441406,
        "Low": 53.19816207885742,
        "Close": 53.63294219970703,
        "Adj Close": 27.83519744873047,
        "Volume": 5022722.0
    },
    "MO": {
        "Open": 43.29999923706055,
        "High": 43.43000030517578,
        "Low": 42.310001373291016,
        "Close": 42.7400016784668,
        "Adj Close": 2.5016517639160156,
        "Volume": 5602800.0
    },
    "MRK": {
        "Open": 52.88167953491211,
        "High": 53.874046325683594,
        "Low": 52.671756744384766,
        "Close": 53.35877990722656,
        "Adj Close": 22.055294036865234,
        "Volume": 7123570.0
    },
    "MS": {
        "Open": 39.84000015258789,
        "High": 40.5,
        "Low": 38.70000076293945,
        "Close": 39.27000045776367,
        "Adj Close": 19.910642623901367,
        "Volume": 5222500.0
    },
    "MSFT": {
        "Open": 28.0,
        "High": 28.274999618530273,
        "Low": 27.5049991607666,
        "Close": 27.549999237060547,
        "Adj Close": 16.82908821105957,
        "Volume": 64522200.0
    },
    "NEE": {
        "Open": 7.166250228881836,
        "High": 7.24875020980835,
        "Low": 7.037499904632568,
        "Close": 7.047500133514404,
        "Adj Close": 3.4522640705108643,
        "Volume": 9882400.0
    },
    "NFLX": {
        "Open": 0.060499999672174454,
        "High": 0.06128599867224693,
        "Low": 0.05535700172185898,
        "Close": 0.0610710009932518,
        "Adj Close": 0.0610710009932518,
        "Volume": 49224000.0
    },
    "NKE": {
        "Open": 5.567500114440918,
        "High": 5.663750171661377,
        "Low": 5.431250095367432,
        "Close": 5.50124979019165,
        "Adj Close": 4.151825428009033,
        "Volume": 9651200.0
    },
    "NOW": {
        "Open": null,
        "High": null,
        "Low": null,
        "Close": null,
        "Adj Close": null,
        "Volume": null
    },
    "NVDA": {
        "Open": 0.10249999910593033,
        "High": 0.108583003282547,
        "Low": 0.09175000339746475,
        "Close": 0.09466700255870819,
        "Adj Close": 0.08679399639368057,
        "Volume": 3798900000.0
    },
    "ORCL": {
        "Open": 10.079999923706055,
        "High": 10.079999923706055,
        "Low": 9.539999961853027,
        "Close": 9.550000190734863,
        "Adj Close": 7.635601043701172,
        "Volume": 56464000.0
    },
    "PEP": {
        "Open": 43.25,
        "High": 44.150001525878906,
        "Low": 43.25,
        "Close": 43.779998779296875,
        "Adj Close": 23.370115280151367,
        "Volume": 3339900.0
    },
    "PFE": {
        "Open": 31.783681869506836,
        "High": 32.23908996582031,
        "Low": 31.622390747070312,
        "Close": 32.13472366333008,
        "Adj Close": 12.543937683105469,
        "Volume": 13440397.0
    },
    "PG": {
        "Open": 44.25,
        "High": 44.529998779296875,
        "Low": 43.584999084472656,
        "Close": 43.845001220703125,
        "Adj Close": 23.457679748535156,
        "Volume": 6014200.0
    },
    "PLTR": {
        "Open": null,
        "High": null,
        "Low": null,
        "Close": null,
        "Adj Close": null,
        "Volume": null
    },
    "PM": {
        "Open": null,
        "High": null,
        "Low": null,
        "Close": null,
        "Adj Close": null,
        "Volume": null
    },
    "PYPL": {
        "Open": null,
        "High": null,
        "Low": null,
        "Close": null,
        "Adj Close": null,
        "Volume": null
    },
    "QCOM": {
        "Open": 18.045000076293945,
        "High": 18.079999923706055,
        "Low": 17.31999969482422,
        "Close": 17.3700008392334,
        "Adj Close": 10.759904861450195,
        "Volume": 49730800.0
    },
    "RTX": {
        "Open": 20.28005027770996,
        "High": 20.449968338012695,
        "Low": 19.757709503173828,
        "Close": 19.826934814453125,
        "Adj Close": 11.894087791442871,
        "Volume": 15972310.0
    },
    "SBUX": {
        "Open": 5.702499866485596,
        "High": 5.762499809265137,
        "Low": 5.612500190734863,
        "Close": 5.635000228881836,
        "Adj Close": 4.181333541870117,
        "Volume": 13383600.0
    },
    "SCHW": {
        "Open": 9.779999732971191,
        "High": 10.010000228881836,
        "Low": 9.619999885559082,
        "Close": 9.710000038146973,
        "Adj Close": 7.0710768699646,
        "Volume": 2718500.0
    },
    "SO": {
        "Open": 28.489999771118164,
        "High": 28.489999771118164,
        "Low": 27.3799991607666,
        "Close": 27.3799991607666,
        "Adj Close": 9.794471740722656,
        "Volume": 3514400.0
    },
    "SPG": {
        "Open": 31.90027618408203,
        "High": 32.02093505859375,
        "Low": 31.63111686706543,
        "Close": 31.853870391845703,
        "Adj Close": 11.694700241088867,
        "Volume": 360289.0
    },
    "T": {
        "Open": 20.407854080200195,
        "High": 20.996978759765625,
        "Low": 20.05286979675293,
        "Close": 20.551359176635742,
        "Adj Close": 4.019896030426025,
        "Volume": 10620334.0
    },
    "TGT": {
        "Open": 31.0,
        "High": 31.450000762939453,
        "Low": 30.31999969482422,
        "Close": 30.75,
        "Adj Close": 18.25935935974121,
        "Volume": 4290300.0
    },
    "TMO": {
        "Open": 19.549999237060547,
        "High": 19.639999389648438,
        "Low": 19.06999969482422,
        "Close": 19.149999618530273,
        "Adj Close": 18.135414123535156,
        "Volume": 431800.0
    },
    "TMUS": {
        "Open": null,
        "High": null,
        "Low": null,
        "Close": null,
        "Adj Close": null,
        "Volume": null
    },
    "TSLA": {
        "Open": null,
        "High": null,
        "Low": null,
        "Close": null,
        "Adj Close": null,
        "Volume": null
    },
    "TXN": {
        "Open": 15.119999885559082,
        "High": 15.220000267028809,
        "Low": 14.399999618530273,
        "Close": 15.0,
        "Adj Close": 9.202431678771973,
        "Volume": 12738600.0
    },
    "UBER": {
        "Open": null,
        "High": null,
        "Low": null,
        "Close": null,
        "Adj Close": null,
        "Volume": null
    },
    "UNH": {
        "Open": 23.760000228881836,
        "High": 23.760000228881836,
        "Low": 21.627500534057617,
        "Close": 21.707500457763672,
        "Adj Close": 16.85778045654297,
        "Volume": 38267600.0
    },
    "UNP": {
        "Open": 15.199999809265137,
        "High": 15.385000228881836,
        "Low": 15.020000457763672,
        "Close": 15.074999809265137,
        "Adj Close": 9.469710350036621,
        "Volume": 2850000.0
    },
    "UPS": {
        "Open": 61.650001525878906,
        "High": 62.91999816894531,
        "Low": 61.650001525878906,
        "Close": 62.34000015258789,
        "Adj Close": 31.126914978027344,
        "Volume": 2655800.0
    },
    "USB": {
        "Open": 20.440000534057617,
        "High": 20.68000030517578,
        "Low": 19.920000076293945,
        "Close": 20.15999984741211,
        "Adj Close": 9.265438079833984,
        "Volume": 4124300.0
    },
    "V": {
        "Open": null,
        "High": null,
        "Low": null,
        "Close": null,
        "Adj Close": null,
        "Volume": null
    },
    "VZ": {
        "Open": 34.273189544677734,
        "High": 35.07358932495117,
        "Low": 34.183258056640625,
        "Close": 34.785804748535156,
        "Adj Close": 10.876919746398926,
        "Volume": 8100651.0
    },
    "WFC": {
        "Open": 23.5,
        "High": 23.670000076293945,
        "Low": 22.350000381469727,
        "Close": 22.729999542236328,
        "Adj Close": 11.910144805908203,
        "Volume": 16543400.0
    },
    "WMT": {
        "Open": 18.0,
        "High": 18.266666412353516,
        "Low": 17.84000015258789,
        "Close": 18.010000228881836,
        "Adj Close": 11.656889915466309,
        "Volume": 22359000.0
    }
}